graphchain/__init__.py
graphchain/core.py
graphchain/py.typed
graphchain/utils.py
graphchain-1.4.0.dist-info/LICENSE
graphchain-1.4.0.dist-info/WHEEL
graphchain-1.4.0.dist-info/METADATA
graphchain-1.4.0.dist-info/RECORD
