Metadata-Version: 2.1
Name: graphchain
Version: 1.4.0
Summary: An efficient cache for the execution of dask graphs.
Home-page: https://github.com/radix-ai/graphchain
Author: Laurent Sorber
Author-email: laurent@radix.ai
Requires-Python: >=3.8,<3.11
Classifier: Programming Language :: Python :: 3
Classifier: Programming Language :: Python :: 3.10
Classifier: Programming Language :: Python :: 3.8
Classifier: Programming Language :: Python :: 3.9
Requires-Dist: cloudpickle (>=1.0.0,<3.0.0)
Requires-Dist: dask (>=2020.12.0)
Requires-Dist: fs-s3fs (>=1,<2)
Requires-Dist: joblib (>=1,<2)
Requires-Dist: lz4 (>=3,<5)
Project-URL: Repository, https://github.com/radix-ai/graphchain
